tinyprove/__init__.py
tinyprove/axiom_defs.py
tinyprove/core.py
tinyprove/inductive.py
tinyprove/ir.py
tinyprove/parser.py
tinyprove-0.1.2.dist-info/METADATA
tinyprove-0.1.2.dist-info/WHEEL
tinyprove-0.1.2.dist-info/top_level.txt
tinyprove-0.1.2.dist-info/RECORD
