Metadata-Version: 2.4
Name: tinyprove
Version: 0.1.2
Summary: Tiny CoC-based theorem prover with inductive types
Project-URL: Homepage, https://github.com/pb1729/tinyprove
Project-URL: Repository, https://github.com/pb1729/tinyprove
Project-URL: Issues, https://github.com/pb1729/tinyprove/issues
Requires-Python: >=3.10
